{"status":"ok","data":{"planet_position":[{"id":0,"name":"Sun","longitude":318.42766815669245,"is_retrograde":false,"position":11,"degree":18.427668156692448,"rasi":{"id":10,"name":"Kumbha","lord":{"id":6,"name":"Saturn","vedic_name":"Shani"}}},{"id":1,"name":"Moon","longitude":106.22013133057285,"is_retrograde":false,"position":4,"degree":16.220131330572855,"rasi":{"id":3,"name":"Karka","lord":{"id":1,"name":"Moon","vedic_name":"Chandra"}}},{"id":2,"name":"Mercury","longitude":298.4035530210966,"is_retrograde":false,"position":10,"degree":28.403553021096627,"rasi":{"id":9,"name":"Makara","lord":{"id":6,"name":"Saturn","vedic_name":"Shani"}}},{"id":3,"name":"Venus","longitude":2.2104291623508523,"is_retrograde":false,"position":1,"degree":2.2104291623508523,"rasi":{"id":0,"name":"Mesha","lord":{"id":4,"name":"Mars","vedic_name":"Kuja"}}},{"id":4,"name":"Mars","longitude":318.8670414304945,"is_retrograde":false,"position":11,"degree":18.86704143049451,"rasi":{"id":10,"name":"Kumbha","lord":{"id":6,"name":"Saturn","vedic_name":"Shani"}}},{"id":5,"name":"Jupiter","longitude":258.1914943204599,"is_retrograde":false,"position":9,"degree":18.191494320459924,"rasi":{"id":8,"name":"Dhanu","lord":{"id":5,"name":"Jupiter","vedic_name":"Guru"}}},{"id":6,"name":"Saturn","longitude":331.7867683880384,"is_retrograde":false,"position":12,"degree":1.7867683880384106,"rasi":{"id":11,"name":"Meena","lord":{"id":5,"name":"Jupiter","vedic_name":"Guru"}}},{"id":100,"name":"Ascendant","longitude":148.3143545449994,"is_retrograde":false,"position":5,"degree":28.31435454499939,"rasi":{"id":4,"name":"Simha","lord":{"id":0,"name":"Sun","vedic_name":"Ravi"}}},{"id":101,"name":"Rahu","longitude":175.37631124532018,"is_retrograde":true,"position":6,"degree":25.37631124532018,"rasi":{"id":5,"name":"Kanya","lord":{"id":2,"name":"Mercury","vedic_name":"Budha"}}},{"id":102,"name":"Ketu","longitude":355.37631124532015,"is_retrograde":true,"position":12,"degree":25.376311245320153,"rasi":{"id":11,"name":"Meena","lord":{"id":5,"name":"Jupiter","vedic_name":"Guru"}}}]}}