{"status":"ok","data":{"planet_position":[{"id":0,"name":"Sun","longitude":236.34984110533503,"is_retrograde":false,"position":8,"degree":26.34984110533503,"rasi":{"id":7,"name":"Vrischika","lord":{"id":4,"name":"Mars","vedic_name":"Kuja"}}},{"id":1,"name":"Moon","longitude":237.33025879164978,"is_retrograde":false,"position":8,"degree":27.330258791649783,"rasi":{"id":7,"name":"Vrischika","lord":{"id":4,"name":"Mars","vedic_name":"Kuja"}}},{"id":2,"name":"Mercury","longitude":216.1406437461055,"is_retrograde":false,"position":8,"degree":6.140643746105496,"rasi":{"id":7,"name":"Vrischika","lord":{"id":4,"name":"Mars","vedic_name":"Kuja"}}},{"id":3,"name":"Venus","longitude":227.11284495774154,"is_retrograde":false,"position":8,"degree":17.112844957741544,"rasi":{"id":7,"name":"Vrischika","lord":{"id":4,"name":"Mars","vedic_name":"Kuja"}}},{"id":4,"name":"Mars","longitude":184.68112560196798,"is_retrograde":false,"position":7,"degree":4.6811256019679774,"rasi":{"id":6,"name":"Tula","lord":{"id":3,"name":"Venus","vedic_name":"Shukra"}}},{"id":5,"name":"Jupiter","longitude":290.6148024305857,"is_retrograde":false,"position":10,"degree":20.614802430585712,"rasi":{"id":9,"name":"Makara","lord":{"id":6,"name":"Saturn","vedic_name":"Shani"}}},{"id":6,"name":"Saturn","longitude":219.29613532127743,"is_retrograde":false,"position":8,"degree":9.296135321277433,"rasi":{"id":7,"name":"Vrischika","lord":{"id":4,"name":"Mars","vedic_name":"Kuja"}}},{"id":100,"name":"Ascendant","longitude":249.79240457362295,"is_retrograde":false,"position":9,"degree":9.792404573622946,"rasi":{"id":8,"name":"Dhanu","lord":{"id":5,"name":"Jupiter","vedic_name":"Guru"}}},{"id":101,"name":"Rahu","longitude":13.213276141924624,"is_retrograde":true,"position":1,"degree":13.213276141924624,"rasi":{"id":0,"name":"Mesha","lord":{"id":4,"name":"Mars","vedic_name":"Kuja"}}},{"id":102,"name":"Ketu","longitude":193.2132761419246,"is_retrograde":true,"position":7,"degree":13.21327614192461,"rasi":{"id":6,"name":"Tula","lord":{"id":3,"name":"Venus","vedic_name":"Shukra"}}}]}}