{"status":"ok","data":{"planet_position":[{"id":0,"name":"Sun","longitude":190.3104058915961,"is_retrograde":false,"position":7,"degree":10.310405891596105,"rasi":{"id":6,"name":"Tula","lord":{"id":3,"name":"Venus","vedic_name":"Shukra"}}},{"id":1,"name":"Moon","longitude":190.0034521308696,"is_retrograde":false,"position":7,"degree":10.00345213086959,"rasi":{"id":6,"name":"Tula","lord":{"id":3,"name":"Venus","vedic_name":"Shukra"}}},{"id":2,"name":"Mercury","longitude":196.58359503699563,"is_retrograde":true,"position":7,"degree":16.583595036995632,"rasi":{"id":6,"name":"Tula","lord":{"id":3,"name":"Venus","vedic_name":"Shukra"}}},{"id":3,"name":"Venus","longitude":225.88595380990466,"is_retrograde":false,"position":8,"degree":15.885953809904663,"rasi":{"id":7,"name":"Vrischika","lord":{"id":4,"name":"Mars","vedic_name":"Kuja"}}},{"id":4,"name":"Mars","longitude":151.32589727575572,"is_retrograde":false,"position":6,"degree":1.3258972757557217,"rasi":{"id":5,"name":"Kanya","lord":{"id":2,"name":"Mercury","vedic_name":"Budha"}}},{"id":5,"name":"Jupiter","longitude":46.09815905385672,"is_retrograde":true,"position":2,"degree":16.09815905385672,"rasi":{"id":1,"name":"Vrishabha","lord":{"id":3,"name":"Venus","vedic_name":"Shukra"}}},{"id":6,"name":"Saturn","longitude":35.42081466153797,"is_retrograde":true,"position":2,"degree":5.4208146615379675,"rasi":{"id":1,"name":"Vrishabha","lord":{"id":3,"name":"Venus","vedic_name":"Shukra"}}},{"id":100,"name":"Ascendant","longitude":291.55098525743836,"is_retrograde":false,"position":10,"degree":21.550985257438356,"rasi":{"id":9,"name":"Makara","lord":{"id":6,"name":"Saturn","vedic_name":"Shani"}}},{"id":101,"name":"Rahu","longitude":85.29507790670648,"is_retrograde":true,"position":3,"degree":25.29507790670648,"rasi":{"id":2,"name":"Mithuna","lord":{"id":2,"name":"Mercury","vedic_name":"Budha"}}},{"id":102,"name":"Ketu","longitude":265.29507790670647,"is_retrograde":true,"position":9,"degree":25.295077906706467,"rasi":{"id":8,"name":"Dhanu","lord":{"id":5,"name":"Jupiter","vedic_name":"Guru"}}}]}}