{
    "status": "ok",
    "data": {
        "planet_position": [
            {
                "id": 0,
                "name": "Sun",
                "longitude": 351.65345365850015,
                "is_retrograde": false,
                "position": 12,
                "degree": 21.653453658500155,
                "rasi": {
                    "id": 11,
                    "name": "Meena",
                    "lord": {
                        "id": 5,
                        "name": "Jupiter",
                        "vedic_name": "Guru"
                    }
                }
            },
            {
                "id": 1,
                "name": "Moon",
                "longitude": 100.85773366871967,
                "is_retrograde": false,
                "position": 4,
                "degree": 10.857733668719675,
                "rasi": {
                    "id": 3,
                    "name": "Karka",
                    "lord": {
                        "id": 1,
                        "name": "Moon",
                        "vedic_name": "Chandra"
                    }
                }
            },
            {
                "id": 2,
                "name": "Mercury",
                "longitude": 353.7787137906564,
                "is_retrograde": true,
                "position": 12,
                "degree": 23.77871379065641,
                "rasi": {
                    "id": 11,
                    "name": "Meena",
                    "lord": {
                        "id": 5,
                        "name": "Jupiter",
                        "vedic_name": "Guru"
                    }
                }
            },
            {
                "id": 3,
                "name": "Venus",
                "longitude": 305.38797866147866,
                "is_retrograde": false,
                "position": 11,
                "degree": 5.387978661478655,
                "rasi": {
                    "id": 10,
                    "name": "Kumbha",
                    "lord": {
                        "id": 6,
                        "name": "Saturn",
                        "vedic_name": "Shani"
                    }
                }
            },
            {
                "id": 4,
                "name": "Mars",
                "longitude": 0.4949508164358356,
                "is_retrograde": false,
                "position": 1,
                "degree": 0.4949508164358356,
                "rasi": {
                    "id": 0,
                    "name": "Mesha",
                    "lord": {
                        "id": 4,
                        "name": "Mars",
                        "vedic_name": "Kuja"
                    }
                }
            },
            {
                "id": 5,
                "name": "Jupiter",
                "longitude": 320.3612517031069,
                "is_retrograde": false,
                "position": 11,
                "degree": 20.361251703106916,
                "rasi": {
                    "id": 10,
                    "name": "Kumbha",
                    "lord": {
                        "id": 6,
                        "name": "Saturn",
                        "vedic_name": "Shani"
                    }
                }
            },
            {
                "id": 6,
                "name": "Saturn",
                "longitude": 358.5011340589907,
                "is_retrograde": false,
                "position": 12,
                "degree": 28.501134058990715,
                "rasi": {
                    "id": 11,
                    "name": "Meena",
                    "lord": {
                        "id": 5,
                        "name": "Jupiter",
                        "vedic_name": "Guru"
                    }
                }
            },
            {
                "id": 100,
                "name": "Ascendant",
                "longitude": 161.65177902497683,
                "is_retrograde": false,
                "position": 6,
                "degree": 11.651779024976832,
                "rasi": {
                    "id": 5,
                    "name": "Kanya",
                    "lord": {
                        "id": 2,
                        "name": "Mercury",
                        "vedic_name": "Budha"
                    }
                }
            },
            {
                "id": 101,
                "name": "Rahu",
                "longitude": 134.88936730773997,
                "is_retrograde": true,
                "position": 5,
                "degree": 14.889367307739974,
                "rasi": {
                    "id": 4,
                    "name": "Simha",
                    "lord": {
                        "id": 0,
                        "name": "Sun",
                        "vedic_name": "Ravi"
                    }
                }
            },
            {
                "id": 102,
                "name": "Ketu",
                "longitude": 314.88936730774,
                "is_retrograde": true,
                "position": 11,
                "degree": 14.889367307739974,
                "rasi": {
                    "id": 10,
                    "name": "Kumbha",
                    "lord": {
                        "id": 6,
                        "name": "Saturn",
                        "vedic_name": "Shani"
                    }
                }
            }
        ]
    }
}